LICENSE.md
MANIFEST.in
README.md
requirements.txt
setup.py
gitless/__init__.py
gitless/core.py
gitless.egg-info/PKG-INFO
gitless.egg-info/SOURCES.txt
gitless.egg-info/dependency_links.txt
gitless.egg-info/entry_points.txt
gitless.egg-info/requires.txt
gitless.egg-info/top_level.txt
gitless/cli/__init__.py
gitless/cli/commit_dialog.py
gitless/cli/file_cmd.py
gitless/cli/gl.py
gitless/cli/gl_branch.py
gitless/cli/gl_checkout.py
gitless/cli/gl_commit.py
gitless/cli/gl_diff.py
gitless/cli/gl_fuse.py
gitless/cli/gl_history.py
gitless/cli/gl_init.py
gitless/cli/gl_merge.py
gitless/cli/gl_publish.py
gitless/cli/gl_remote.py
gitless/cli/gl_resolve.py
gitless/cli/gl_status.py
gitless/cli/gl_switch.py
gitless/cli/gl_tag.py
gitless/cli/gl_track.py
gitless/cli/gl_untrack.py
gitless/cli/helpers.py
gitless/cli/pprint.py