Metadata-Version: 1.1
Name: gitless
Version: 0.8.8
Summary: A version control system built on top of Git
Home-page: http://gitless.com
Author: Santiago Perez De Rosso
Author-email: sperezde@csail.mit.edu
License: MIT
Platform: UNKNOWN
Classifier: Development Status :: 2 - Pre-Alpha
Classifier: Intended Audience :: Developers
Classifier: License :: OSI Approved :: MIT License
Classifier: Natural Language :: English
Classifier: Programming Language :: Python
Classifier: Programming Language :: Python :: 2
Classifier: Programming Language :: Python :: 3
Classifier: Topic :: Software Development :: Version Control
